tests/__init__.py
tests/conftest.py
tests/test_clerap.py
tests/test_css.py
tests/test_css_utils.py
tests/test_engine.py
tests/test_navrap.py
tests/test_sourcer.py
tests/test_svg.py
tests/test_svg_antennas.py
tests/test_yarap.py
yawrap/__init__.py
yawrap/_engine.py
yawrap/_navrap.py
yawrap/_sourcer.py
yawrap/_yawrap.py
yawrap/clerap.py
yawrap/elements_def.py
yawrap/six.py
yawrap/utils.py
yawrap-0.4.10.dist-info/LICENSE
yawrap-0.4.10.dist-info/METADATA
yawrap-0.4.10.dist-info/WHEEL
yawrap-0.4.10.dist-info/top_level.txt
yawrap-0.4.10.dist-info/RECORD
