Metadata-Version: 1.2
Name: yawrap
Version: 0.4.10
Summary: simple generator of complex html reports
Home-page: https://gitlab.com/kamichal/yawrap
Author: Michał Kaczmarczyk
Author-email: michal.s.kaczmarczyk@gmail.com
Maintainer: Michał Kaczmarczyk
Maintainer-email: michal.s.kaczmarczyk@gmail.com
License: MIT license
Keywords: html generator
Platform: UNKNOWN
Classifier: Development Status :: 4 - Beta
Classifier: Intended Audience :: Developers
Classifier: Intended Audience :: Information Technology
Classifier: Intended Audience :: Science/Research
Classifier: Intended Audience :: System Administrators
Classifier: Intended Audience :: Telecommunications Industry
Classifier: License :: OSI Approved :: MIT License
Classifier: Operating System :: OS Independent
Classifier: Programming Language :: Python :: 2
Classifier: Programming Language :: Python :: 2.7
Classifier: Programming Language :: Python :: 3
Classifier: Programming Language :: Python :: 3.5
Classifier: Programming Language :: Python :: 3.6
Classifier: Programming Language :: Python :: 3.7
Classifier: Programming Language :: Python :: 3.8
Classifier: Programming Language :: Python :: Implementation :: PyPy
Classifier: Programming Language :: Python
Classifier: Topic :: Database :: Front-Ends
Classifier: Topic :: Documentation
Classifier: Topic :: Internet :: WWW/HTTP :: Browsers
Classifier: Topic :: Internet :: WWW/HTTP :: Dynamic Content
Classifier: Topic :: Internet :: WWW/HTTP
Classifier: Topic :: Scientific/Engineering :: Visualization
Classifier: Topic :: Software Development :: Code Generators
Classifier: Topic :: Utilities
